randon/__init__.py
randon-0.0.6.dist-info/LICENSE
randon-0.0.6.dist-info/METADATA
randon-0.0.6.dist-info/WHEEL
randon-0.0.6.dist-info/top_level.txt
randon-0.0.6.dist-info/RECORD
