Metadata-Version: 2.1
Name: randon
Version: 0.0.6
Summary: makes random number
Author: Technical Earth
Author-email: technicalearth0@gmail.com
License: UNKNOWN
Keywords: python,random,number,add,multiply,PYPI
Platform: UNKNOWN
Classifier: Development Status :: 1 - Planning
Classifier: Intended Audience :: Developers
Classifier: Programming Language :: Python :: 3
Classifier: Operating System :: Unix
Classifier: Operating System :: MacOS :: MacOS X
Classifier: Operating System :: Microsoft :: Windows
License-File: LICENSE
